pybrgr/__init__.py
pybrgr/main.py
pybrgr-0.1.1.dist-info/METADATA
pybrgr-0.1.1.dist-info/WHEEL
pybrgr-0.1.1.dist-info/entry_points.txt
pybrgr-0.1.1.dist-info/top_level.txt
pybrgr-0.1.1.dist-info/RECORD
