Metadata-Version: 2.1
Name: pybrgr
Version: 0.1.1
Summary: A pybrgr python package.
Home-page: https://github.com/pybrgr/pybrgr
Author: Chris Pryer
Author-email: christophpryer@gmail.com
License: PUBLIC
Platform: UNKNOWN
